Workbook
Name Aporte: Planilha1!$D$15
Name patrimonio: Planilha1!$D$18
Name qtd_anos: Planilha1!$D$16
Name Rendimento_Carteira: Planilha1!$D$10
Name salario: Planilha1!$B$9:$D$9
Name tx_mensal: Planilha1!$D$17

Sheet Planilha1
B8: CONFIGURAÇÕES
B9: Salário | D9: 3500
B10: Rendimento Carteira | D10: 0.006
B11: Sugestão de Investimento | D11: =D9*30% -> 1050
B14: INVESTIMENTO MENSAL
B15: Quanto investir por mês ? | D15: 500
B16: Por Quantos Anos ? | D16: 10
B17: Taxa de Rendimento mensal ? | D17: =Rendimento_Carteira -> 0.006
B18: Patrimônio acumulado ? | D18: =FV(tx_mensal,qtd_anos*12,Aporte*-1) -> 87501.505
B19: Dividendos Mensais ? | D19: =patrimonio*tx_mensal -> 525.00903
B22: Cenários | D22: Dividendo
A23: 2 | B23: Quanto em 2 Anos? | C23: =FV($D$17,$A23*12,$D$15*-1) -> 12865.608 | D23: =C23*tx_mensal -> 77.193646
A24: 5 | B24: Quanto em 5 Anos? | C24: =FV($D$17,$A24*12,$D$15*-1) -> 35982.368 | D24: =C24*tx_mensal -> 215.89421
A25: 10 | B25: Quanto em 10 Anos? | C25: =FV($D$17,$A25*12,$D$15*-1) -> 87501.505 | D25: =C25*tx_mensal -> 525.00903
A26: 20 | B26: Quanto em 20 Anos? | C26: =FV($D$17,$A26*12,$D$15*-1) -> 266881.17 | D26: =C26*tx_mensal -> 1601.287
A27: 30 | B27: Quanto em 30 Anos? | C27: =FV($D$17,$A27*12,$D$15*-1) -> 634612.72 | D27: =C27*tx_mensal -> 3807.6763
B30: PERFIL | C30: Agressivo
B31: VALOR A SER INVESTIDO NO MÊS | C31: =Aporte -> 500
B33: TIPO DE FII | C33: Percentual Sugerido | D33: Valor
B34: PAPEL | C34: =VLOOKUP($C$30&" - "&B34,Planilha2!A3:D20,4,FALSE) -> 0.5 | D34: =C34*$C$31 -> 250
B35: TIJOLOS | C35: =VLOOKUP($C$30&" - "&B35,Planilha2!A4:D21,4,FALSE) -> 0.1 | D35: =C35*$C$31 -> 50
B36: HIBRIDOS | C36: =VLOOKUP($C$30&" - "&B36,Planilha2!A5:D22,4,FALSE) -> 0.05 | D36: =C36*$C$31 -> 25
B37: FOF'S | C37: =VLOOKUP($C$30&" - "&B37,Planilha2!A6:D23,4,FALSE) -> 0.05 | D37: =C37*$C$31 -> 25
B38: DESENVOLVIMENTO | C38: =VLOOKUP($C$30&" - "&B38,Planilha2!A7:D24,4,FALSE) -> 0.2 | D38: =C38*$C$31 -> 100
B39: HOTELARIAS | C39: =VLOOKUP($C$30&" - "&B39,Planilha2!A8:D25,4,FALSE) -> 0.1 | D39: =C39*$C$31 -> 50
B40: TOTAL | D40: =SUM(D34:D39) -> 500

Sheet Planilha2
A2: CHAVE | B2: PERFIL | C2: TIPOS DE FII | D2: %
A3: =B3&" - "&C3 -> Conservador - PAPEL | B3: Conservador | C3: PAPEL | D3: 0.3
A4: =B4&" - "&C4 -> Conservador - TIJOLOS | B4: Conservador | C4: TIJOLOS | D4: 0.5
A5: =B5&" - "&C5 -> Conservador - HIBRIDOS | B5: Conservador | C5: HIBRIDOS | D5: 0.1
A6: =B6&" - "&C6 -> Conservador - FOF'S | B6: Conservador | C6: FOF'S | D6: 0.1
A7: =B7&" - "&C7 -> Conservador - DESENVOLVIMENTO | B7: Conservador | C7: DESENVOLVIMENTO | D7: 0
A8: =B8&" - "&C8 -> Conservador - HOTELARIAS | B8: Conservador | C8: HOTELARIAS | D8: 0
A9: =B9&" - "&C9 -> Moderado - PAPEL | B9: Moderado | C9: PAPEL | D9: 0.32
A10: =B10&" - "&C10 -> Moderado - TIJOLOS | B10: Moderado | C10: TIJOLOS | D10: 0.4
A11: =B11&" - "&C11 -> Moderado - HIBRIDOS | B11: Moderado | C11: HIBRIDOS | D11: 0.08
A12: =B12&" - "&C12 -> Moderado - FOF'S | B12: Moderado | C12: FOF'S | D12: 0.1
A13: =B13&" - "&C13 -> Moderado - DESENVOLVIMENTO | B13: Moderado | C13: DESENVOLVIMENTO | D13: 0.05
A14: =B14&" - "&C14 -> Moderado - HOTELARIAS | B14: Moderado | C14: HOTELARIAS | D14: 0.05
... A20: =B20&" - "&C20 -> Agressivo - HOTELARIAS | B20: Agressivo | C20: HOTELARIAS | D20: 0.1
